databpy/__init__.py
databpy/addon.py
databpy/array.py
databpy/attribute.py
databpy/collection.py
databpy/material.py
databpy/object.py
databpy/utils.py
databpy/vdb.py
databpy/nodes/__init__.py
databpy/nodes/appending.py
databpy/nodes/generating.py
databpy/nodes/utils.py
databpy-0.5.1.dist-info/licenses/LICENSE
databpy-0.5.1.dist-info/METADATA
databpy-0.5.1.dist-info/WHEEL
databpy-0.5.1.dist-info/top_level.txt
databpy-0.5.1.dist-info/RECORD
