Metadata-Version: 2.4
Name: databpy
Version: 0.5.1
Summary: A data-oriented wrapper library for the Blender Python API
Maintainer-email: Brady Johnston <brady.johnston@me.com>
Project-URL: Homepage, https://bradyajohnston.github.io/databpy
Project-URL: Repository, https://github.com/bradyajohnston/databpy
Project-URL: Documentation, https://bradyajohnston.github.io/databpy
Keywords: blender,python,numpy
Requires-Python: ~=3.11.0
License-File: LICENSE
Requires-Dist: numpy<2.0,>=1.24.0
Provides-Extra: bpy
Requires-Dist: bpy>=4.5; extra == "bpy"
Provides-Extra: test
Requires-Dist: pytest; extra == "test"
Requires-Dist: pytest-cov; extra == "test"
Provides-Extra: dev
Requires-Dist: fake-bpy-module; extra == "dev"
Requires-Dist: polars; extra == "dev"
Provides-Extra: docs
Requires-Dist: quartodoc; extra == "docs"
Requires-Dist: jupyter; extra == "docs"
Requires-Dist: polars; extra == "docs"
Dynamic: license-file
